switch_case/__init__.py
switch_case/case.py
switch_case/curry.py
switch_case/infix.py
switch_case/nil.py
switch_case/operator.py
switch_case/switch.py
tests/__init__.py
tests/test_case.py
tests/test_curry.py
tests/test_operator.py
tests/test_switch.py
tests/test_switch_case.py
switch_case-1.5.dist-info/LICENSE
switch_case-1.5.dist-info/METADATA
switch_case-1.5.dist-info/WHEEL
switch_case-1.5.dist-info/top_level.txt
switch_case-1.5.dist-info/RECORD
