Metadata-Version: 2.1
Name: switch_case
Version: 1.5
Summary: Switch-case statement for Python
Home-page: https://github.com/nikitanovosibirsk/switch_case
Author: Nikita Tsvetkov
Author-email: nikitanovosibirsk@yandex.com
License: MIT
Platform: UNKNOWN
Classifier: License :: OSI Approved :: MIT License
Classifier: Programming Language :: Python :: 3.6
Classifier: Programming Language :: Python :: 3.7
Classifier: Programming Language :: Python :: 3.8
Classifier: Programming Language :: Python :: 3.9
Classifier: Programming Language :: Python :: 3.10
Classifier: Intended Audience :: Developers
Requires-Python: >=3.6
License-File: LICENSE
